LICENSE.txt
README.txt
bootstrap.py
buildout.cfg
checkdocs.cfg
lxml.cfg
nginx.cfg
setup.py
varnish.cfg
docs/HISTORY.txt
docs/TODO.txt
docs/compiler.graffle
docs/compiler.pdf
examples/content.html
examples/extra.html
examples/rules.xml
examples/theme.html
examples/ploneorg/default.xml
examples/ploneorg/documentation.html
examples/ploneorg/plone.html
lib/xdv/__init__.py
lib/xdv/boilerplate.xsl
lib/xdv/compiler.py
lib/xdv/compiler.xsl
lib/xdv/cssrules.py
lib/xdv/filter.xsl
lib/xdv/resolvers.py
lib/xdv/run.py
lib/xdv/update-namespace.xsl
lib/xdv/utils.py
lib/xdv.egg-info/PKG-INFO
lib/xdv.egg-info/SOURCES.txt
lib/xdv.egg-info/dependency_links.txt
lib/xdv.egg-info/entry_points.txt
lib/xdv.egg-info/not-zip-safe
lib/xdv.egg-info/requires.txt
lib/xdv.egg-info/top_level.txt
lib/xdv/tests/__init__.py
lib/xdv/tests/absolute_rules.xml
lib/xdv/tests/absolute_theme.html
lib/xdv/tests/tests.py
lib/xdv/tests/001/README.rst
lib/xdv/tests/001/content.html
lib/xdv/tests/001/output.html
lib/xdv/tests/001/rules.xml
lib/xdv/tests/001/theme.html
lib/xdv/tests/001/xpaths.txt
lib/xdv/tests/002/README.rst
lib/xdv/tests/002/content.html
lib/xdv/tests/002/output.html
lib/xdv/tests/002/rules.xml
lib/xdv/tests/002/theme.html
lib/xdv/tests/002/xpaths.txt
lib/xdv/tests/003/content.html
lib/xdv/tests/003/output.html
lib/xdv/tests/003/rules.xml
lib/xdv/tests/003/theme.html
lib/xdv/tests/003/xpaths.txt
lib/xdv/tests/004/content.html
lib/xdv/tests/004/output.html
lib/xdv/tests/004/rules.xml
lib/xdv/tests/004/theme.html
lib/xdv/tests/004/xpaths.txt
lib/xdv/tests/005/content.html
lib/xdv/tests/005/output.html
lib/xdv/tests/005/rules.xml
lib/xdv/tests/005/theme.html
lib/xdv/tests/005/xpaths.txt
lib/xdv/tests/006/content.html
lib/xdv/tests/006/output.html
lib/xdv/tests/006/rules.xml
lib/xdv/tests/006/theme.html
lib/xdv/tests/006/xpaths.txt
lib/xdv/tests/007/content.html
lib/xdv/tests/007/output.html
lib/xdv/tests/007/rules.xml
lib/xdv/tests/007/theme.html
lib/xdv/tests/007/xpaths.txt
lib/xdv/tests/008/README.txt
lib/xdv/tests/008/content.html
lib/xdv/tests/008/output.html
lib/xdv/tests/008/rules.xml
lib/xdv/tests/008/theme.html
lib/xdv/tests/008/xpaths.txt
lib/xdv/tests/009/content.html
lib/xdv/tests/009/output.html
