Metadata-Version: 1.0
Name: xdv
Version: 0.3
Summary: XDV implements a subset of Deliverance using a pure XSLT engine. With XDV, you
Home-page: UNKNOWN
Author: Paul Everitt, Laurence Rowe and Martin Aspeli.
Author-email: laurence@lrowe.co.uk
License: New BSD
Platform: UNKNOWN
